setup.py
pieqc/__init__.py
pieqc.egg-info/PKG-INFO
pieqc.egg-info/SOURCES.txt
pieqc.egg-info/dependency_links.txt
pieqc.egg-info/top_level.txt