Metadata-Version: 2.1
Name: pieqc
Version: 0.0.1
Summary: test pie
Author: fmalone
License: UNKNOWN
Platform: UNKNOWN
